h2o_discovery/__init__.py
h2o_discovery/_version.py
h2o_discovery/error.py
h2o_discovery/model.py
h2o_discovery/py.typed
h2o_discovery/_internal/client.py
h2o_discovery/_internal/compat.py
h2o_discovery/_internal/config.py
h2o_discovery/_internal/load.py
h2o_discovery/_internal/lookup.py
h2o_cloud_discovery-3.2.0.dist-info/METADATA
h2o_cloud_discovery-3.2.0.dist-info/WHEEL
h2o_cloud_discovery-3.2.0.dist-info/licenses/LICENSE
h2o_cloud_discovery-3.2.0.dist-info/RECORD
