Metadata-Version: 2.4
Name: h2o-cloud-discovery
Version: 3.2.0
Summary: H2O Cloud Discovery Python CLient
Project-URL: Documentation, https://github.com/h2oai/cloud-discovery-py#readme
Project-URL: Issues, https://github.com/h2oai/cloud-discovery-py/issues
Project-URL: Source, https://github.com/h2oai/cloud-discovery-py
Author-email: "H2O.ai" <support@h2o.ai>
License-Expression: Apache-2.0
License-File: LICENSE
Classifier: Intended Audience :: Developers
Classifier: Operating System :: OS Independent
Classifier: Topic :: Internet
Classifier: Topic :: Scientific/Engineering :: Artificial Intelligence
Classifier: Topic :: Security
Classifier: Topic :: Utilities
Requires-Python: >=3.9
Requires-Dist: httpx>=0.23
Requires-Dist: httpx>=0.25.1; python_version >= '3.14'
Requires-Dist: tomli>=1.1.0; python_version < '3.11'
